{
  "version": "7",
  "dialect": "sqlite",
  "entries": [
    {
      "idx": 0,
      "version": "6",
      "when": 1784139336507,
      "tag": "0000_strange_praxagora",
      "breakpoints": true
    },
    {
      "idx": 1,
      "version": "6",
      "when": 1784141643095,
      "tag": "0001_wealthy_steel_serpent",
      "breakpoints": true
    },
    {
      "idx": 2,
      "version": "6",
      "when": 1784176910710,
      "tag": "0002_cloudy_abomination",
      "breakpoints": true
    }
  ]
}